oceandata/__init__.py
oceandata/chl/__init__.py
oceandata/chl/valente.py
oceandata/export_production/__init__.py
oceandata/export_production/mouw.py
oceandata/gdp.py
oceandata/mapps.py
oceandata/primary_production/__init__.py
oceandata/primary_production/buitenhuis.py
oceandata/primary_production/mattei.py
oceandata/primary_production/pp_decorr_time.py
oceandata/primary_production/primary_production.py
oceandata/seabass_pic.py
oceandata-0.3.1.dist-info/LICENSE
oceandata-0.3.1.dist-info/WHEEL
oceandata-0.3.1.dist-info/METADATA
oceandata-0.3.1.dist-info/RECORD
