Metadata-Version: 2.1
Name: oceandata
Version: 0.3.1
Summary: 
Author: Bror Jonsson
Author-email: brorfred@gmail.com
Requires-Python: >=3.7.1,<4.0
Classifier: Programming Language :: Python :: 3
Classifier: Programming Language :: Python :: 3.8
Classifier: Programming Language :: Python :: 3.9
Classifier: Programming Language :: Python :: 3.10
Requires-Dist: click (>=7.0,<8.0)
Requires-Dist: numpy (>1.14)
Requires-Dist: pandas (>1.1)
Requires-Dist: requests (>=2.21,<3.0)
Requires-Dist: xlrd (>=2.0.1,<3.0.0)
